<Students><Student><Name>Amit</Name><Age>21</Age><Marks><Math>75</Math><Science>80</Science><English>85</English></Marks></Student><Student><Name>Sneha</Name><Age>20</Age><Marks><Math>90</Math><Science>93</Science><English>87</English></Marks></Student><Student><Name>Ravi</Name><Age>22</Age><Marks><Math>70</Math><Science>65</Science><English>75</English></Marks></Student><Student><Name>Meera</Name><Age>19</Age><Marks><Math>95</Math><Science>97</Science><English>100</English></Marks></Student></Students>